weighted_stats/__init__.py
weighted_stats/weighted_t_test.py
wstats/__init__.py
wstats/weighted_t_test.py
wstats-0.0.99.dist-info/LICENSE
wstats-0.0.99.dist-info/METADATA
wstats-0.0.99.dist-info/WHEEL
wstats-0.0.99.dist-info/top_level.txt
wstats-0.0.99.dist-info/RECORD
