Metadata-Version: 2.1
Name: wstats
Version: 0.0.99
Summary: An implementation of a few weighted statistics
Home-page: https://github.com/scottyler89/weighted_stats/
Author: Scott Tyler
Author-email: scottyler89@gmail.com
Classifier: Programming Language :: Python :: 3
Classifier: License :: OSI Approved :: MIT License
Classifier: Operating System :: OS Independent
License-File: LICENSE
Requires-Dist: numba
Requires-Dist: numpy
Requires-Dist: scipy
